gb_io/lib.abi3.so
gb_io/py.typed
gb_io/lib.pyi
gb_io/__init__.py
gb_io/lib/build.rs
gb_io/lib/lib.rs
gb_io/lib/built.rs
gb_io/lib/coa.rs
gb_io/lib/pyfile.rs
gb_io/lib/reader.rs
gb_io-0.3.7.dist-info/WHEEL
gb_io-0.3.7.dist-info/METADATA
gb_io-0.3.7.dist-info/RECORD
gb_io-0.3.7.dist-info/licenses/COPYING
