Metadata-Version: 2.4
Name: gb-io
Version: 0.3.7
Classifier: Development Status :: 4 - Beta
Classifier: Intended Audience :: Developers
Classifier: Intended Audience :: Science/Research
Classifier: Intended Audience :: Healthcare Industry
Classifier: License :: OSI Approved :: MIT License
Classifier: Programming Language :: Rust
Classifier: Programming Language :: Python :: 3.7
Classifier: Programming Language :: Python :: 3.8
Classifier: Programming Language :: Python :: 3.9
Classifier: Programming Language :: Python :: 3.10
Classifier: Programming Language :: Python :: 3.11
Classifier: Programming Language :: Python :: 3.12
Classifier: Programming Language :: Python :: 3.13
Classifier: Programming Language :: Python :: 3.14
Classifier: Programming Language :: Python :: Implementation :: CPython
Classifier: Programming Language :: Python :: Implementation :: PyPy
Classifier: Topic :: Scientific/Engineering :: Bio-Informatics
Classifier: Topic :: Scientific/Engineering :: Medical Science Apps.
Classifier: Topic :: Software Development :: Libraries :: Python Modules
Classifier: Typing :: Typed
License-File: COPYING
Summary: A Python interface to gb-io, a fast GenBank parser and serializer written in Rust.
Keywords: genbank,parser,sequence,record
Author-email: Martin Larralde <martin.larralde@embl.de>
Requires-Python: >=3.7
Project-URL: Homepage, https://github.com/althonos/gb-io.py/
Project-URL: Bug Tracker, https://github.com/althonos/gb-io.py/issues
Project-URL: Changelog, https://github.com/althonos/gb-io.py/blob/master/CHANGELOG.md
Project-URL: Coverage, https://codecov.io/gh/althonos/gb-io.py/
Project-URL: Documentation, https://gb-io.readthedocs.io/
Project-URL: Builds, https://github.com/althonos/gb-io.py/actions/
Project-URL: PyPI, https://pypi.org/project/gb-io
Project-URL: PiWheels, https://www.piwheels.org/project/gb-io/
